AUTHORS.rst
CONTRIBUTING.rst
HISTORY.rst
LICENSE
MANIFEST.in
README.md
README.rst
VERSION
piomart
requirements.txt
setup.cfg
setup.py
docs/example_workflow.rst
docs/importing_piomart.rst
docs/index.rst
docs/installation.rst
docs/piomart_download.rst
piomart/__init__.py
piomart/piomart.py
piomart/piomart_download.py
piomart.egg-info/PKG-INFO
piomart.egg-info/SOURCES.txt
piomart.egg-info/dependency_links.txt
piomart.egg-info/entry_points.txt
piomart.egg-info/requires.txt
piomart.egg-info/top_level.txt
tests/CHECKSUMS
tests/Gorilla_gorilla.gorGor4.93.gtf.gz
tests/Macaca_fascicularis.Macaca_fascicularis_5.0.93.gtf.gz
tests/__init__.py
tests/adj_onset_deseq2_results.csv
tests/boop.csv
tests/duplicate_values.csv
tests/ensembl_no_versions.tsv
tests/floop.csv
tests/homo_sapiens.json
tests/inexact_test_df.csv
tests/mart_export.txt
tests/no_index_name.csv
tests/no_ver_dep_par.csv
tests/no_ver_dep_par_annotated.csv
tests/no_version.csv
tests/no_versions_annotated.csv
tests/no_versions_inexact.csv
tests/problem_json.csv
tests/test_deseq.csv
tests/test_download_piomart.py
tests/test_mocks.py
tests/test_piomart.py
tests/.ipynb_checkpoints/Untitled-checkpoint.ipynb